{
  "id": "0a7eb8ef31364e179cd22686dbb8d148",
  "title": "Engines of Fury: Initiates_EditionAudience",
  "description": "Engines of Fury: Initiates_EditionAudience",
  "categories": [
    {
      "path": "audience"
    },
    {
      "path": "public"
    }
  ],
  "namespace": "503e0694c7f6438fb9865df48eca5e67",
  "status": "ACTIVE",
  "creationDate": "2025-09-25T06:39:47.704Z",
  "lastModifiedDate": "2025-09-25T20:08:18.732Z",
  "entitlementName": "0a7eb8ef31364e179cd22686dbb8d148",
  "entitlementType": "AUDIENCE",
  "itemType": "DURABLE",
  "developer": "Prosperity Joint Limited",
  "developerId": "o-l445dm4plsfen7rkc7f9bzhsvkng73",
  "endOfSupport": false,
  "requiresSecureAccount": false,
  "unsearchable": false
}