{
  "id": "0e28af6ee0694de89eae370264e1ed0f",
  "title": "Scholar Krond Skin & Feat Pack",
  "description": "Scholar Krond Skin & Feat Pack",
  "categories": [
    {
      "path": "addons"
    }
  ],
  "namespace": "7e508f543b05465abe3a935960eb70ac",
  "status": "ACTIVE",
  "creationDate": "2023-04-21T14:49:47.205Z",
  "lastModifiedDate": "2023-05-15T15:01:36.619Z",
  "customAttributes": {
    "CanRunOffline": {
      "type": "STRING",
      "value": "true"
    }
  },
  "entitlementName": "0e28af6ee0694de89eae370264e1ed0f",
  "entitlementType": "EXECUTABLE",
  "itemType": "DURABLE",
  "releaseInfo": [],
  "developer": "Codename Entertainment",
  "developerId": "o-3kpjwtwqwfl2p9wdwvpad7yqz4kt6c",
  "eulaIds": [
    "egstore"
  ],
  "endOfSupport": false,
  "requiresSecureAccount": false,
  "unsearchable": true
}