{
  "id": "115e9da00c164e19a88ae5535df418e4",
  "title": "alnitak GeneralAudience",
  "description": "alnitak GeneralAudience",
  "keyImages": [],
  "categories": [
    {
      "path": "audience"
    },
    {
      "path": "public"
    }
  ],
  "namespace": "2015d187216e4b33b88edee66282e4a1",
  "status": "ACTIVE",
  "creationDate": "2021-08-26T01:23:46.826Z",
  "lastModifiedDate": "2021-11-01T20:06:30.865Z",
  "customAttributes": {},
  "entitlementName": "115e9da00c164e19a88ae5535df418e4",
  "entitlementType": "AUDIENCE",
  "itemType": "DURABLE",
  "releaseInfo": [],
  "developer": "Another Indie Studio Limited",
  "developerId": "o-ze7grkplqlrzc92lepkjv4xpaj7gn8",
  "eulaIds": [
    "egstore"
  ],
  "endOfSupport": false,
  "requiresSecureAccount": false,
  "unsearchable": true
}