{
  "id": "18d05f5542bc45658cf5a4a922c49b0d",
  "title": "XOCIETY Playtest_DemoAudience",
  "description": "XOCIETY Playtest_DemoAudience",
  "categories": [
    {
      "path": "audience"
    },
    {
      "path": "public"
    }
  ],
  "namespace": "7a544209697a4373988b8f1724a7c90d",
  "status": "ACTIVE",
  "creationDate": "2025-08-12T23:55:05.893Z",
  "lastModifiedDate": "2025-12-20T03:28:26.135Z",
  "entitlementName": "18d05f5542bc45658cf5a4a922c49b0d",
  "entitlementType": "AUDIENCE",
  "itemType": "DURABLE",
  "developer": "TXCELERATOR PTE. LTD.",
  "developerId": "o-nxhr33hw52labu42x22let7desxs7j",
  "endOfSupport": false,
  "requiresSecureAccount": false,
  "unsearchable": false
}