{
  "id": "1d6e4e6b7ddb407ba9339d0afc52ebc6",
  "title": "ontario Deluxe Edition audience",
  "description": "ontario Deluxe Edition audience",
  "categories": [
    {
      "path": "audience"
    },
    {
      "path": "public"
    }
  ],
  "namespace": "ac98aa34584648f2b71152e509191c1c",
  "status": "ACTIVE",
  "creationDate": "2022-08-05T09:13:08.733Z",
  "lastModifiedDate": "2024-01-15T11:57:52.106Z",
  "customAttributes": {
    "SupportedPlatforms": {
      "type": "STRING",
      "value": "Windows"
    }
  },
  "entitlementName": "1d6e4e6b7ddb407ba9339d0afc52ebc6",
  "entitlementType": "AUDIENCE",
  "itemType": "DURABLE",
  "releaseInfo": [],
  "developer": "Saber Interactive",
  "developerId": "o-2xlz78ngz5ubvus9sff9blglee43uk",
  "eulaIds": [
    "egstore"
  ],
  "endOfSupport": false,
  "ageGatings": {},
  "applicationId": "",
  "requiresSecureAccount": false,
  "unsearchable": true
}