{
  "id": "2d5385221de94b66b5a04375097ed52e",
  "title": "Whitefire Shaman 3_ConsumableAudience",
  "description": "Whitefire Shaman 3_ConsumableAudience",
  "categories": [
    {
      "path": "audience"
    },
    {
      "path": "public"
    }
  ],
  "namespace": "6688f6ac60ba489e87ebd7f454c6bded",
  "status": "ACTIVE",
  "creationDate": "2026-06-09T01:57:29.487Z",
  "lastModifiedDate": "2026-06-12T01:10:21.577Z",
  "entitlementName": "2d5385221de94b66b5a04375097ed52e",
  "entitlementType": "AUDIENCE",
  "itemType": "CONSUMABLE",
  "developer": "NETMARBLE",
  "developerId": "o-5elvruguh7ffugwhd2rfu9jmzzjsr6",
  "useCount": 1,
  "endOfSupport": false,
  "requiresSecureAccount": false,
  "unsearchable": false
}