{
  "id": "2dfd407dcac04fb3a31b896e0fffa58d",
  "title": "MONGIL: STAR DIVE_Desktop_BaseGameAudience",
  "description": "MONGIL: STAR DIVE_Desktop_BaseGameAudience",
  "categories": [
    {
      "path": "audience"
    },
    {
      "path": "public"
    }
  ],
  "namespace": "6688f6ac60ba489e87ebd7f454c6bded",
  "status": "ACTIVE",
  "creationDate": "2025-04-21T10:10:50.209Z",
  "lastModifiedDate": "2025-06-06T22:30:18.847Z",
  "entitlementName": "2dfd407dcac04fb3a31b896e0fffa58d",
  "entitlementType": "AUDIENCE",
  "itemType": "DURABLE",
  "developer": "NETMARBLE",
  "developerId": "o-5elvruguh7ffugwhd2rfu9jmzzjsr6",
  "endOfSupport": false,
  "requiresSecureAccount": false,
  "unsearchable": false
}