{
  "id": "3577deb80d4f4c5e8ed2c656504e6aae",
  "title": "BLACKSHARD - Soundtrack",
  "description": "BLACKSHARD - Soundtrack",
  "keyImages": [
    {
      "type": "DieselGameBox",
      "url": "https://cdn1.epicgames.com/spt-assets/bf41f197884944bb8e01e3dcfa494a61/blackshard-64cjn.jpg",
      "md5": "fc9fd0cc8f01fbe49091a6c058127d86",
      "width": 2560,
      "height": 1440,
      "size": 1497290,
      "uploadedDate": "2025-06-18T15:14:37.981Z",
      "alt": "BLACKSHARD BLACKSHARD - Soundtrack Offer"
    },
    {
      "type": "DieselGameBoxTall",
      "url": "https://cdn1.epicgames.com/spt-assets/bf41f197884944bb8e01e3dcfa494a61/blackshard-6bi9g.png",
      "md5": "cbab647b998efe99cb82edce743da036",
      "width": 1200,
      "height": 1600,
      "size": 1751062,
      "uploadedDate": "2025-06-18T15:08:38.298Z",
      "alt": "Download BLACKSHARD BLACKSHARD - Soundtrack Offer"
    }
  ],
  "categories": [
    {
      "path": "digitalextras"
    },
    {
      "path": "applications"
    }
  ],
  "namespace": "5479820bfa8945979cc05ef8d37e1a40",
  "status": "ACTIVE",
  "creationDate": "2025-06-24T14:00:03.428Z",
  "lastModifiedDate": "2025-06-24T14:00:03.428Z",
  "customAttributes": {
    "FolderName": {
      "type": "STRING",
      "value": "DigitalBLACKSHARD761d0"
    }
  },
  "entitlementName": "3577deb80d4f4c5e8ed2c656504e6aae",
  "entitlementType": "EXECUTABLE",
  "itemType": "DURABLE",
  "releaseInfo": [
    {
      "id": "405935e9-2ab7-4109-9a9c-a6dd6e0a362b",
      "appId": "3847869b6d3344ee8a86734d951752f0",
      "platform": [
        "Win32",
        "Windows",
        "Mac"
      ]
    }
  ],
  "developer": "Plug In Digital SAS",
  "developerId": "o-yw5ga5z854qs64ld82qey3dz2d7z32",
  "endOfSupport": false,
  "requiresSecureAccount": false,
  "unsearchable": false
}