{
  "id": "3f2eba1b849f4c7889dc1e6a5e61701f",
  "title": "Cash (40) Offer 3_ConsumableAudience",
  "description": "Cash (40) Offer 3_ConsumableAudience",
  "categories": [
    {
      "path": "audience"
    },
    {
      "path": "public"
    }
  ],
  "namespace": "65cb6825df5b405694fda26c3426ea88",
  "status": "ACTIVE",
  "creationDate": "2025-04-28T10:57:55.863Z",
  "lastModifiedDate": "2025-04-28T10:57:55.863Z",
  "entitlementName": "3f2eba1b849f4c7889dc1e6a5e61701f",
  "entitlementType": "AUDIENCE",
  "itemType": "CONSUMABLE",
  "developer": "BoomBit Games Ltd",
  "developerId": "o-pke4j36x4pbt99tdf4htzegenguwny",
  "useCount": 1,
  "endOfSupport": false,
  "requiresSecureAccount": false,
  "unsearchable": false
}