{
  "id": "414f37cb922a40469e0091437fa4ee87",
  "title": "S12 Shockgun Weapon Bundle",
  "description": "S12 Shockgun Weapon Bundle",
  "categories": [
    {
      "path": "addons"
    }
  ],
  "namespace": "affc33b82405457595a032f00284abd2",
  "status": "ACTIVE",
  "creationDate": "2023-03-28T17:50:24.088Z",
  "lastModifiedDate": "2023-03-30T23:02:37.701Z",
  "customAttributes": {
    "CanRunOffline": {
      "type": "STRING",
      "value": "true"
    }
  },
  "entitlementName": "414f37cb922a40469e0091437fa4ee87",
  "entitlementType": "EXECUTABLE",
  "itemType": "DURABLE",
  "releaseInfo": [],
  "developer": "Tripwire Interactive",
  "developerId": "o-2baznhy8tfh7fmyb55ul656v7ggt7r",
  "eulaIds": [
    "egstore"
  ],
  "endOfSupport": false,
  "requiresSecureAccount": false,
  "unsearchable": true
}