{
  "id": "46947a65801f487380fb62cf2fb96858",
  "title": "Cyclopes Project Snickers audience",
  "description": "Cyclopes Project Snickers audience",
  "keyImages": [],
  "categories": [
    {
      "path": "audience"
    },
    {
      "path": "public"
    }
  ],
  "namespace": "6009be9994c2409099588cde6f3a5ed0",
  "status": "ACTIVE",
  "creationDate": "2025-06-03T11:04:50.125Z",
  "lastModifiedDate": "2025-09-09T14:56:20.808Z",
  "customAttributes": {
    "SupportedPlatforms": {
      "type": "STRING",
      "value": "Windows"
    }
  },
  "entitlementName": "46947a65801f487380fb62cf2fb96858",
  "entitlementType": "AUDIENCE",
  "itemType": "DURABLE",
  "releaseInfo": [],
  "developer": "Paradox Interactive",
  "developerId": "o-tjvfg6rejs6h86qa7k9aa64rrgbxxb",
  "eulaIds": [
    "egstore"
  ],
  "endOfSupport": false,
  "ageGatings": {},
  "applicationId": "",
  "requiresSecureAccount": false,
  "unsearchable": true
}