{
  "id": "5431eb1cfa3049c58b5ed047d978c57a",
  "title": "Love pack",
  "description": "Love pack",
  "keyImages": [
    {
      "type": "DieselGameBox",
      "url": "https://cdn1.epicgames.com/spt-assets/d149efc702eb4aeb8553346bf6f8777e/bullet-yeeters-9qxql.jpg",
      "md5": "f65b741435b3aa416d47cf0a1affbf09",
      "width": 2560,
      "height": 1440,
      "size": 1205878,
      "uploadedDate": "2025-07-24T11:42:44.526Z",
      "alt": "BULLET YEETERS Love pack Offer"
    },
    {
      "type": "DieselGameBoxTall",
      "url": "https://cdn1.epicgames.com/spt-assets/d149efc702eb4aeb8553346bf6f8777e/bullet-yeeters-y0xoa.jpg",
      "md5": "cb7948cfe4e50a692d1ba09517cea32d",
      "width": 1200,
      "height": 1600,
      "size": 813132,
      "uploadedDate": "2025-07-24T11:42:52.990Z",
      "alt": "Download BULLET YEETERS Love pack Offer"
    }
  ],
  "categories": [
    {
      "path": "addons"
    }
  ],
  "namespace": "7432d892de1944e4978052cd7b85a7f8",
  "status": "ACTIVE",
  "creationDate": "2025-07-24T20:13:45.485Z",
  "lastModifiedDate": "2025-07-24T20:13:45.485Z",
  "entitlementName": "5431eb1cfa3049c58b5ed047d978c57a",
  "entitlementType": "EXECUTABLE",
  "itemType": "DURABLE",
  "developer": "Brightika, Inc.",
  "developerId": "o-2cjye9ryu4k24hdvys8ksfqvp5p4fy",
  "endOfSupport": false,
  "requiresSecureAccount": false,
  "unsearchable": false
}