{
  "id": "6a1dde0923c64f09b2bcb3d470c53014",
  "title": "Rare Item With Gems_ConsumableAudience",
  "description": "Rare Item With Gems_ConsumableAudience",
  "categories": [
    {
      "path": "audience"
    },
    {
      "path": "public"
    }
  ],
  "namespace": "65cb6825df5b405694fda26c3426ea88",
  "status": "ACTIVE",
  "creationDate": "2025-04-08T07:54:34.430Z",
  "lastModifiedDate": "2025-06-05T12:01:22.070Z",
  "entitlementName": "6a1dde0923c64f09b2bcb3d470c53014",
  "entitlementType": "AUDIENCE",
  "itemType": "CONSUMABLE",
  "developer": "BoomBit Games Ltd",
  "developerId": "o-pke4j36x4pbt99tdf4htzegenguwny",
  "useCount": 1,
  "endOfSupport": false,
  "requiresSecureAccount": false,
  "unsearchable": false
}