{
  "id": "70660903f11d459f82392036884bff86",
  "title": "DevGeneralAudience",
  "description": "DevGeneralAudience",
  "categories": [
    {
      "path": "audience"
    },
    {
      "path": "public"
    }
  ],
  "namespace": "29c24db4bfa847df8d3774a249e13d19",
  "status": "ACTIVE",
  "creationDate": "2025-02-12T11:11:00.403Z",
  "lastModifiedDate": "2025-12-16T12:48:46.928Z",
  "entitlementName": "70660903f11d459f82392036884bff86",
  "entitlementType": "AUDIENCE",
  "itemType": "DURABLE",
  "releaseInfo": [],
  "developer": "Anti-Ded GameDev",
  "developerId": "o-zvw73whvrtdehys6zuk5q6qb2eehh8",
  "endOfSupport": false,
  "requiresSecureAccount": false,
  "unsearchable": false
}