{
  "id": "749adbc4b2664c75ac2c522fffe3a504",
  "title": "ErosGeneralAudience",
  "description": "ErosGeneralAudience",
  "keyImages": [],
  "categories": [
    {
      "path": "audience"
    },
    {
      "path": "public"
    }
  ],
  "namespace": "699c2dc3694c4156befa26cad5c65505",
  "status": "ACTIVE",
  "creationDate": "2021-06-16T03:42:01.608Z",
  "lastModifiedDate": "2021-11-30T16:53:41.496Z",
  "customAttributes": {
    "SupportedPlatforms": {
      "type": "STRING",
      "value": "Windows"
    }
  },
  "entitlementName": "749adbc4b2664c75ac2c522fffe3a504",
  "entitlementType": "AUDIENCE",
  "itemType": "DURABLE",
  "releaseInfo": [],
  "developer": "Frogwares",
  "developerId": "o-rlw9u3sem84g2hc3ur36dqnp7wul3j",
  "eulaIds": [
    "egstore"
  ],
  "installModes": [],
  "endOfSupport": false,
  "ageGatings": {},
  "applicationId": "",
  "requiresSecureAccount": false,
  "unsearchable": true
}