{
  "id": "759777e027e94a749ff02fa2d50c5aff",
  "title": "mellowyellow BDL21 audience",
  "description": "mellowyellow BDL21 audience",
  "categories": [
    {
      "path": "audience"
    },
    {
      "path": "public"
    }
  ],
  "namespace": "428115def4ca4deea9d69c99c5a5a99e",
  "status": "ACTIVE",
  "creationDate": "2024-09-06T09:04:16.892Z",
  "lastModifiedDate": "2025-05-06T15:38:10.740Z",
  "customAttributes": {
    "SupportedPlatforms": {
      "type": "STRING",
      "value": "Windows"
    }
  },
  "entitlementName": "759777e027e94a749ff02fa2d50c5aff",
  "entitlementType": "AUDIENCE",
  "itemType": "DURABLE",
  "developer": "Bungie",
  "developerId": "o-49lqsefbl6zr5sy3ztak77ej97cuvh",
  "eulaIds": [
    "egstore"
  ],
  "endOfSupport": false,
  "requiresSecureAccount": false,
  "unsearchable": true
}