{
  "id": "75ca71a1c64b4a34ab9f88693a20f289",
  "title": "Quiet is the Eyes",
  "description": "Quiet is the Eyes",
  "keyImages": [
    {
      "type": "DieselGameBox",
      "url": "https://cdn1.epicgames.com/spt-assets/0789ab1813a642d48d6078c5865dd195/quiet-is-the-eyes-46okx.png",
      "md5": "7a7be511ae81177e5a39d3b2adbafc97",
      "width": 2560,
      "height": 1440,
      "size": 1399915,
      "uploadedDate": "2025-03-08T20:16:44.653Z",
      "alt": "Quiet is the Eyes Offer"
    },
    {
      "type": "DieselGameBoxTall",
      "url": "https://cdn1.epicgames.com/spt-assets/0789ab1813a642d48d6078c5865dd195/quiet-is-the-eyes-1wqea.png",
      "md5": "0779708245bfd86f235417d658aef4c0",
      "width": 1200,
      "height": 1600,
      "size": 975907,
      "uploadedDate": "2025-03-08T20:33:29.583Z",
      "alt": "Download Quiet is the Eyes Offer"
    }
  ],
  "categories": [
    {
      "path": "games"
    },
    {
      "path": "applications"
    }
  ],
  "namespace": "6ddd68a396524aa1b9fe3819b3ae478d",
  "status": "ACTIVE",
  "creationDate": "2025-04-11T18:01:05.409Z",
  "lastModifiedDate": "2025-04-11T18:01:05.409Z",
  "customAttributes": {
    "FolderName": {
      "type": "STRING",
      "value": "QuietistheEyes7559f"
    }
  },
  "entitlementName": "75ca71a1c64b4a34ab9f88693a20f289",
  "entitlementType": "EXECUTABLE",
  "itemType": "DURABLE",
  "releaseInfo": [
    {
      "id": "786c53f8-7095-4b80-8c9a-ee4e5a3e9e22",
      "appId": "bd9c2be448584935af4438c2bd779b32",
      "platform": [
        "Windows"
      ]
    }
  ],
  "developer": "USC Games",
  "developerId": "o-fhlqgs7et8mhncsshxnxdbp2vtvs37",
  "endOfSupport": false,
  "requiresSecureAccount": false,
  "unsearchable": false
}