{
  "id": "81913de70cba47beb72ccc6f7e4fa2c7",
  "title": "FortniteDeco_JunoContent",
  "description": "FortniteDeco_JunoContent",
  "categories": [
    {
      "path": "applications"
    }
  ],
  "namespace": "fn",
  "status": "ACTIVE",
  "creationDate": "2026-06-01T16:25:11.104Z",
  "lastModifiedDate": "2026-06-01T16:25:13.336Z",
  "customAttributes": {
    "remove_for_account_deprovision": {
      "type": "STRING",
      "value": "true"
    },
    "UseAccessControl": {
      "type": "STRING",
      "value": "false"
    },
    "AdditionalCommandLine": {
      "type": "STRING",
      "value": "-epicapp=FortniteDeco -IslandOverride=playlist_juno"
    },
    "CanSkipKoreanIdVerification": {
      "type": "STRING",
      "value": "true"
    }
  },
  "entitlementName": "81913de70cba47beb72ccc6f7e4fa2c7",
  "entitlementType": "EXECUTABLE",
  "itemType": "DURABLE",
  "releaseInfo": [
    {
      "id": "a8926f43daf4429b8bb00c3b7562b8a7",
      "appId": "144384e2269a475fa8c58123780de407",
      "platform": [
        "Windows"
      ]
    }
  ],
  "developer": "Epic Games",
  "developerId": "o-aa83a0a9bc45e98c80c1b1c9d92e9e",
  "endOfSupport": false,
  "requiresSecureAccount": false,
  "unsearchable": false
}