{
  "id": "8325b3ee3dfa48feb553fbe3175d3971",
  "title": "The Battle of Polytopia",
  "description": "The Battle of Polytopia",
  "keyImages": [
    {
      "type": "DieselGameBox",
      "url": "https://cdn1.epicgames.com/spt-assets/b312dfc1b33d459daa55a67d53a56223/the-battle-of-polytopia-1oqil.png",
      "md5": "0d7be303d1972efd1da23952fbf8c464",
      "width": 2560,
      "height": 1440,
      "size": 1191842,
      "uploadedDate": "2025-05-09T13:30:40.651Z",
      "alt": "The Battle of Polytopia Offer"
    },
    {
      "type": "DieselGameBoxTall",
      "url": "https://cdn1.epicgames.com/spt-assets/b312dfc1b33d459daa55a67d53a56223/the-battle-of-polytopia-b1dbq.png",
      "md5": "3fa525dad321f225aebf478f08bd854e",
      "width": 1200,
      "height": 1600,
      "size": 780831,
      "uploadedDate": "2025-05-09T13:30:39.889Z",
      "alt": "Download The Battle of Polytopia Offer"
    }
  ],
  "categories": [
    {
      "path": "games"
    },
    {
      "path": "applications"
    }
  ],
  "namespace": "c28a4972ae574f27af0304e6ac625009",
  "status": "ACTIVE",
  "creationDate": "2022-03-29T12:05:42.378Z",
  "lastModifiedDate": "2025-05-28T21:18:02.794Z",
  "customAttributes": {
    "AllowUriCmdArgs": {
      "type": "STRING",
      "value": "true"
    },
    "AllowMultipleInstances": {
      "type": "STRING",
      "value": "TRUE"
    },
    "FolderName": {
      "type": "STRING",
      "value": "TheBattleofPolytopiaACfMZ"
    }
  },
  "entitlementName": "8325b3ee3dfa48feb553fbe3175d3971",
  "entitlementType": "EXECUTABLE",
  "itemType": "DURABLE",
  "releaseInfo": [
    {
      "id": "5f00e4b8659240a6ba292cde6406778a",
      "appId": "3ce838d7a25c49368a22918b56e88f2a",
      "platform": [
        "Windows",
        "Mac"
      ]
    }
  ],
  "developer": "Midjiwan AB",
  "developerId": "o-2mkf2lxtzafg97txffccjfxmjmj3sb",
  "eulaIds": [],
  "endOfSupport": false,
  "ageGatings": {},
  "applicationId": "fghi4567gQHZO5pMhb8Rl12RbDY3BRTF",
  "requiresSecureAccount": false,
  "unsearchable": false
}