{
  "id": "8758308eaccd4873918917c0ee875e4f",
  "title": "DevGeneralAudience",
  "description": "DevGeneralAudience",
  "categories": [
    {
      "path": "audience"
    },
    {
      "path": "public"
    }
  ],
  "namespace": "4275cb8b5c9f4d7cb4892d793eabebfd",
  "status": "ACTIVE",
  "creationDate": "2025-05-19T20:08:59.720Z",
  "lastModifiedDate": "2025-05-19T23:13:39.525Z",
  "entitlementName": "8758308eaccd4873918917c0ee875e4f",
  "entitlementType": "AUDIENCE",
  "itemType": "DURABLE",
  "releaseInfo": [],
  "developer": "GSC Game World Global LTD.",
  "developerId": "o-e4pcmp7frwrbjnn6q4tc3a642ud2x8",
  "endOfSupport": false,
  "requiresSecureAccount": false,
  "unsearchable": false
}