{
  "id": "8e89a2de3dcd47bb907711125d3bd335",
  "title": "Nicktoons & The Dice of Destiny - Deluxe Edition_EditionAudience",
  "description": "Nicktoons & The Dice of Destiny - Deluxe Edition_EditionAudience",
  "categories": [
    {
      "path": "audience"
    },
    {
      "path": "public"
    }
  ],
  "namespace": "a4dcace1e96444d89dbafcf5239b37fb",
  "status": "ACTIVE",
  "creationDate": "2025-08-18T18:12:41.627Z",
  "lastModifiedDate": "2025-09-30T16:00:14.945Z",
  "entitlementName": "8e89a2de3dcd47bb907711125d3bd335",
  "entitlementType": "AUDIENCE",
  "itemType": "DURABLE",
  "developer": "GameMill Entertainment, LLC",
  "developerId": "o-6pngcyakaef8a2mll9fdarpn9zecgm",
  "endOfSupport": false,
  "requiresSecureAccount": false,
  "unsearchable": false
}