{
  "id": "939367b7a74b489fb24bb015c3d377d4",
  "title": "Commandos: Origins - DLC2_AddonAudience",
  "description": "Commandos: Origins - DLC2_AddonAudience",
  "categories": [
    {
      "path": "audience"
    },
    {
      "path": "public"
    }
  ],
  "namespace": "7c64b0352fb7449082d7331141b36d97",
  "status": "ACTIVE",
  "creationDate": "2025-11-10T08:36:26.116Z",
  "lastModifiedDate": "2026-04-02T06:18:52.037Z",
  "entitlementName": "939367b7a74b489fb24bb015c3d377d4",
  "entitlementType": "AUDIENCE",
  "itemType": "DURABLE",
  "developer": "Kalypso Media Group GmbH",
  "developerId": "o-37ss7wypkskvyj58j9s7hhltxtujac",
  "endOfSupport": false,
  "requiresSecureAccount": false,
  "unsearchable": false
}