{
  "id": "9431f7d0b3974478a57617a44ff9baf4",
  "title": "Early Age Economy Premium Pass_ConsumableAudience",
  "description": "Early Age Economy Premium Pass_ConsumableAudience",
  "categories": [
    {
      "path": "audience"
    },
    {
      "path": "public"
    }
  ],
  "namespace": "65cb6825df5b405694fda26c3426ea88",
  "status": "ACTIVE",
  "creationDate": "2025-05-28T19:01:53.440Z",
  "lastModifiedDate": "2025-05-28T19:01:53.440Z",
  "entitlementName": "9431f7d0b3974478a57617a44ff9baf4",
  "entitlementType": "AUDIENCE",
  "itemType": "CONSUMABLE",
  "developer": "BoomBit Games Ltd",
  "developerId": "o-pke4j36x4pbt99tdf4htzegenguwny",
  "useCount": 1,
  "endOfSupport": false,
  "requiresSecureAccount": false,
  "unsearchable": false
}