{
  "id": "97ac6991d8f74cb4a15a17a2bab8aa3c",
  "title": "Digital Art Book_DigitalExtraAudience",
  "description": "Digital Art Book_DigitalExtraAudience",
  "categories": [
    {
      "path": "audience"
    },
    {
      "path": "public"
    }
  ],
  "namespace": "0ae7da2330914e3293c76e88ad0bcf5d",
  "status": "ACTIVE",
  "creationDate": "2025-08-01T09:58:25.913Z",
  "lastModifiedDate": "2025-08-14T08:48:12.148Z",
  "entitlementName": "97ac6991d8f74cb4a15a17a2bab8aa3c",
  "entitlementType": "AUDIENCE",
  "itemType": "DURABLE",
  "developer": "Megabit Publishing",
  "developerId": "o-b6qxjupub3vwqr6he56tqn6jcdlkuj",
  "endOfSupport": false,
  "requiresSecureAccount": false,
  "unsearchable": false
}