{
  "id": "982da3dbf5f5449284e792a0e8b9ffb1",
  "title": "DevGeneralAudience",
  "description": "DevGeneralAudience",
  "categories": [
    {
      "path": "audience"
    },
    {
      "path": "public"
    }
  ],
  "namespace": "6afc7187605b458e89e3d40d46871a51",
  "status": "ACTIVE",
  "creationDate": "2023-04-04T00:46:39.355Z",
  "lastModifiedDate": "2025-06-19T12:42:13.389Z",
  "entitlementName": "982da3dbf5f5449284e792a0e8b9ffb1",
  "entitlementType": "AUDIENCE",
  "itemType": "DURABLE",
  "releaseInfo": [],
  "developer": "Path Games",
  "developerId": "o-uu69b8dk2vy3k6lm7qqv5zd9emdp3q",
  "endOfSupport": false,
  "requiresSecureAccount": false,
  "unsearchable": false
}