{
  "id": "9c46317377a241138083982240d4f9ef",
  "title": "Testing_EditionAudience",
  "description": "Testing_EditionAudience",
  "categories": [
    {
      "path": "audience"
    },
    {
      "path": "public"
    }
  ],
  "namespace": "04cc0c5713994f33a4acba1c4272cfff",
  "status": "ACTIVE",
  "creationDate": "2025-06-24T13:49:41.255Z",
  "lastModifiedDate": "2025-06-24T13:49:41.884Z",
  "entitlementName": "9c46317377a241138083982240d4f9ef",
  "entitlementType": "AUDIENCE",
  "itemType": "DURABLE",
  "developer": "Astragon Entertainment GmbH",
  "developerId": "o-rq9c97g8tttn6czdh2kd9vubqbunvf",
  "endOfSupport": false,
  "requiresSecureAccount": false,
  "unsearchable": false
}