{
  "id": "9f7f282859f54dfea959971738b774e1",
  "title": "bisque ID 11 Audience",
  "description": "bisque ID 11 Audience",
  "keyImages": [],
  "categories": [
    {
      "path": "audience"
    },
    {
      "path": "public"
    }
  ],
  "namespace": "d34cf6aeceb94c579af0236fe1185b79",
  "status": "ACTIVE",
  "creationDate": "2021-09-09T17:28:00.499Z",
  "lastModifiedDate": "2022-05-11T22:32:03.112Z",
  "customAttributes": {},
  "entitlementName": "9f7f282859f54dfea959971738b774e1",
  "entitlementType": "AUDIENCE",
  "itemType": "DURABLE",
  "releaseInfo": [],
  "developer": "1939 Games",
  "developerId": "o-48w8whx3gtk4g452567d6vll4sfsxu",
  "eulaIds": [
    "egstore"
  ],
  "installModes": [],
  "endOfSupport": false,
  "ageGatings": {},
  "applicationId": "",
  "requiresSecureAccount": false,
  "unsearchable": true
}