{
  "id": "9fd8c4eca2ef4e369afbac6c40af697e",
  "title": "This is the Police_Android_BaseGameAudience",
  "description": "This is the Police_Android_BaseGameAudience",
  "categories": [
    {
      "path": "audience"
    },
    {
      "path": "public"
    }
  ],
  "namespace": "f5e1592d41da4d7aaf31cc5379a1b5dd",
  "status": "ACTIVE",
  "creationDate": "2025-02-25T06:39:05.087Z",
  "lastModifiedDate": "2025-02-25T06:39:05.231Z",
  "entitlementName": "9fd8c4eca2ef4e369afbac6c40af697e",
  "entitlementType": "AUDIENCE",
  "itemType": "DURABLE",
  "developer": "Handy Games",
  "developerId": "o-ekk92wx8mesnmsvbseequvnt38mzu6",
  "endOfSupport": false,
  "requiresSecureAccount": false,
  "unsearchable": false
}