{
  "id": "a69ee823b9434594b703ab7c486ba4fd",
  "title": "DevGeneralAudience",
  "description": "DevGeneralAudience",
  "categories": [
    {
      "path": "audience"
    },
    {
      "path": "public"
    }
  ],
  "namespace": "a82500fe59684055ae864e098779165a",
  "status": "ACTIVE",
  "creationDate": "2025-06-23T09:10:44.288Z",
  "lastModifiedDate": "2025-06-23T09:10:44.471Z",
  "entitlementName": "a69ee823b9434594b703ab7c486ba4fd",
  "entitlementType": "AUDIENCE",
  "itemType": "DURABLE",
  "releaseInfo": [],
  "developer": "Cyber Temple Games LLC",
  "developerId": "o-3x2enp2eqtrcdq94lrml4ftlvzs2xv",
  "endOfSupport": false,
  "requiresSecureAccount": false,
  "unsearchable": false
}