{
  "id": "a95a25c2544a46fb984435022b77e151",
  "title": "第一场雪·头饰_ConsumableAudience",
  "description": "第一场雪·头饰_ConsumableAudience",
  "categories": [
    {
      "path": "audience"
    },
    {
      "path": "public"
    }
  ],
  "namespace": "1fa6d3090390423eb8bf033e265727f7",
  "status": "ACTIVE",
  "creationDate": "2025-12-11T01:40:36.302Z",
  "lastModifiedDate": "2025-12-11T01:40:36.302Z",
  "entitlementName": "a95a25c2544a46fb984435022b77e151",
  "entitlementType": "AUDIENCE",
  "itemType": "CONSUMABLE",
  "developer": "A PLUS ENTERTAINMENT PTE. LTD.",
  "developerId": "o-3levmxsvharzuflcaxvz5k5ejphpht",
  "useCount": 1,
  "endOfSupport": false,
  "requiresSecureAccount": false,
  "unsearchable": false
}