{
  "id": "ae6943e4cc8c4a88abac8cf37448d64c",
  "title": "FortniteMedic_JunoContent",
  "description": "FortniteMedic_JunoContent",
  "categories": [
    {
      "path": "applications"
    }
  ],
  "namespace": "fn",
  "status": "ACTIVE",
  "creationDate": "2026-06-01T16:28:26.281Z",
  "lastModifiedDate": "2026-06-01T16:28:28.490Z",
  "customAttributes": {
    "remove_for_account_deprovision": {
      "type": "STRING",
      "value": "true"
    },
    "UseAccessControl": {
      "type": "STRING",
      "value": "false"
    },
    "AdditionalCommandLine": {
      "type": "STRING",
      "value": "-epicapp=FortniteMedic -IslandOverride=playlist_juno"
    },
    "CanSkipKoreanIdVerification": {
      "type": "STRING",
      "value": "true"
    }
  },
  "entitlementName": "ae6943e4cc8c4a88abac8cf37448d64c",
  "entitlementType": "EXECUTABLE",
  "itemType": "DURABLE",
  "releaseInfo": [
    {
      "id": "cc1fdb2ea5a24b26b37d0e4ec86cfd48",
      "appId": "84cffb41dae6471790af0d57b7486dc8",
      "platform": [
        "Windows"
      ]
    }
  ],
  "developer": "Epic Games",
  "developerId": "o-aa83a0a9bc45e98c80c1b1c9d92e9e",
  "endOfSupport": false,
  "requiresSecureAccount": false,
  "unsearchable": false
}