{
  "id": "b142373326f64aea967613a157fffa67",
  "title": "Special offer54_ConsumableAudience",
  "description": "Special offer54_ConsumableAudience",
  "categories": [
    {
      "path": "audience"
    },
    {
      "path": "public"
    }
  ],
  "namespace": "6688f6ac60ba489e87ebd7f454c6bded",
  "status": "ACTIVE",
  "creationDate": "2026-04-22T11:57:10.408Z",
  "lastModifiedDate": "2026-04-22T11:57:10.408Z",
  "entitlementName": "b142373326f64aea967613a157fffa67",
  "entitlementType": "AUDIENCE",
  "itemType": "CONSUMABLE",
  "developer": "NETMARBLE",
  "developerId": "o-5elvruguh7ffugwhd2rfu9jmzzjsr6",
  "useCount": 1,
  "endOfSupport": false,
  "requiresSecureAccount": false,
  "unsearchable": false
}