{
  "id": "b9f0ead0636348a88955dd7805721189",
  "title": "Silicon - Crossroads of the World Collection audience",
  "description": "Silicon - Crossroads of the World Collection audience",
  "categories": [
    {
      "path": "audience"
    },
    {
      "path": "public"
    }
  ],
  "namespace": "eb9cdf6dbe4b47fc8ba474017023476a",
  "status": "ACTIVE",
  "creationDate": "2023-10-19T21:21:22.622Z",
  "lastModifiedDate": "2025-01-28T00:48:29.268Z",
  "customAttributes": {
    "SupportedPlatforms": {
      "type": "STRING",
      "value": "Windows"
    }
  },
  "entitlementName": "b9f0ead0636348a88955dd7805721189",
  "entitlementType": "AUDIENCE",
  "itemType": "DURABLE",
  "releaseInfo": [],
  "developer": "2K Games, Inc.",
  "developerId": "o-37m6jbj5wcvrcvm4wusv7nazdfvbjk",
  "eulaIds": [
    "egstore"
  ],
  "endOfSupport": false,
  "ageGatings": {},
  "applicationId": "",
  "requiresSecureAccount": false,
  "unsearchable": true
}