{
  "id": "bc167bb1378d4f0391c797987d9403a8",
  "title": "The Lord of the Rings: Return to Moria™ Durin's Folk",
  "description": "The Durin's Folk Expansion is coming in Fall 2025! Continue the fight to restore Moria with an expanded end-game story, exciting new game mechanics, plus many unrevealed secrets!  Please wishlist today and check back for more information soon!",
  "keyImages": [
    {
      "type": "DieselGameBox",
      "url": "https://cdn1.epicgames.com/spt-assets/2ae760629a384d5199cbefc612db7ac8/the-lord-of-the-rings-return-to-moria-loirw.png",
      "md5": "bbb7f4f4e6fbead1ec10c16b9a76b04e",
      "width": 2560,
      "height": 1440,
      "size": 3900080,
      "uploadedDate": "2025-08-08T21:34:17.428Z",
      "alt": "The Lord of The Rings Return to Moria The Lord of the Rings: Return to Moria™ Durin's Folk Offer"
    },
    {
      "type": "DieselGameBoxTall",
      "url": "https://cdn1.epicgames.com/spt-assets/2ae760629a384d5199cbefc612db7ac8/the-lord-of-the-rings-return-to-moria-4hyko.png",
      "md5": "e6d2193d00d8dfd8bae42397bf4944d1",
      "width": 1200,
      "height": 1600,
      "size": 2394915,
      "uploadedDate": "2025-08-08T21:34:20.071Z",
      "alt": "Download The Lord of The Rings Return to Moria The Lord of the Rings: Return to Moria™ Durin's Folk Offer"
    }
  ],
  "categories": [
    {
      "path": "addons"
    }
  ],
  "namespace": "1d6b5762a1d643a4830481c44d59abfb",
  "status": "ACTIVE",
  "creationDate": "2025-08-27T17:02:33.405Z",
  "lastModifiedDate": "2025-08-27T17:02:33.405Z",
  "entitlementName": "bc167bb1378d4f0391c797987d9403a8",
  "entitlementType": "EXECUTABLE",
  "itemType": "DURABLE",
  "developer": "North Beach Games",
  "developerId": "o-nwx4cr9ugyq97j23tjkxj5mbdw86qw",
  "endOfSupport": false,
  "requiresSecureAccount": false,
  "unsearchable": false
}