{
  "id": "bfb6ebb782a5487fa5994048ab7127a1",
  "title": "Fuga: Melodies of Steel 3 - Halloween Costume Pack",
  "description": "The dramatic RPG Fuga: Melodies of Steel series is now complete!",
  "keyImages": [
    {
      "type": "DieselGameBox",
      "url": "https://cdn1.epicgames.com/spt-assets/c6ae6ed70d80493490017c75d087aeec/fuga-melodies-of-steel-3-yxjzc.jpg",
      "md5": "f14a91db73785dbb606ad14d26cae4e6",
      "width": 2560,
      "height": 1440,
      "size": 651628,
      "uploadedDate": "2025-07-25T02:22:44.978Z",
      "alt": "Fuga: Melodies of Steel 3 Fuga: Melodies of Steel 3 - Halloween Costume Pack Offer"
    },
    {
      "type": "DieselGameBoxTall",
      "url": "https://cdn1.epicgames.com/spt-assets/c6ae6ed70d80493490017c75d087aeec/fuga-melodies-of-steel-3-15cra.jpg",
      "md5": "532dbf8331834321ff5e0990d58549d0",
      "width": 1200,
      "height": 1600,
      "size": 712181,
      "uploadedDate": "2025-07-25T02:22:55.469Z",
      "alt": "Download Fuga: Melodies of Steel 3 Fuga: Melodies of Steel 3 - Halloween Costume Pack Offer"
    }
  ],
  "categories": [
    {
      "path": "addons"
    }
  ],
  "namespace": "2fd168b5526d4e15a84b53a6c0484f8f",
  "status": "ACTIVE",
  "creationDate": "2025-09-18T01:00:20.920Z",
  "lastModifiedDate": "2025-09-18T01:00:20.920Z",
  "customAttributes": {},
  "entitlementName": "bfb6ebb782a5487fa5994048ab7127a1",
  "entitlementType": "EXECUTABLE",
  "itemType": "DURABLE",
  "releaseInfo": [],
  "developer": "CyberConnect2 Co., Ltd.",
  "developerId": "o-29vjjace9q9pzwgrhfbclu6p4cymua",
  "endOfSupport": false,
  "applicationId": "",
  "requiresSecureAccount": false,
  "unsearchable": false
}