{
  "id": "c85d9bdcf8c04619875fbe44891461ec",
  "title": "Recruitment Support Pack(M)_ConsumableAudience",
  "description": "Recruitment Support Pack(M)_ConsumableAudience",
  "categories": [
    {
      "path": "audience"
    },
    {
      "path": "public"
    }
  ],
  "namespace": "c5af2aba801c4c66add65784696e6806",
  "status": "ACTIVE",
  "creationDate": "2025-06-25T04:09:26.526Z",
  "lastModifiedDate": "2025-07-23T22:52:00.523Z",
  "entitlementName": "c85d9bdcf8c04619875fbe44891461ec",
  "entitlementType": "AUDIENCE",
  "itemType": "CONSUMABLE",
  "developer": "CENTURY NETWORK (HONG KONG) LIMITED",
  "developerId": "o-3qk8hg3g7dfzl7pe2y8vd79se2sqda",
  "useCount": 1,
  "endOfSupport": false,
  "requiresSecureAccount": false,
  "unsearchable": false
}