{
  "id": "ccb8a8ef5fbd41b1a7ace658b5145ae4",
  "title": "y2edition audience",
  "description": "y2edition audience",
  "keyImages": [],
  "categories": [
    {
      "path": "audience"
    },
    {
      "path": "public"
    }
  ],
  "namespace": "f640a0c1648147fea7e81565b45a3003",
  "status": "ACTIVE",
  "creationDate": "2025-08-05T14:43:03.494Z",
  "lastModifiedDate": "2025-12-11T14:59:52.407Z",
  "customAttributes": {
    "SupportedPlatforms": {
      "type": "STRING",
      "value": "Windows"
    }
  },
  "entitlementName": "ccb8a8ef5fbd41b1a7ace658b5145ae4",
  "entitlementType": "AUDIENCE",
  "itemType": "DURABLE",
  "releaseInfo": [],
  "developer": "Focus Entertainment Publishing",
  "developerId": "o-wt4zxeetmq6jem7qp4pkssr46aenj5",
  "eulaIds": [
    "egstore"
  ],
  "endOfSupport": false,
  "ageGatings": {},
  "applicationId": "",
  "requiresSecureAccount": false,
  "unsearchable": true
}