{
  "id": "daf05c7b040f41bfaec80178d159206c",
  "title": "Hellmaster: The Legend of Dante",
  "description": "Hellmaster: The Legend of Dante",
  "keyImages": [
    {
      "type": "DieselGameBox",
      "url": "https://cdn1.epicgames.com/spt-assets/234d2a56e9ab4e689b1a7f1c723f8d09/hellmaster-the-legend-of-dante-1my1f.png",
      "md5": "4e90b685c402da9557e884f3636f7a20",
      "width": 2560,
      "height": 1440,
      "size": 3650101,
      "uploadedDate": "2025-05-11T16:28:43.875Z",
      "alt": "Hellmaster: The Legend of Dante Offer"
    },
    {
      "type": "DieselGameBoxTall",
      "url": "https://cdn1.epicgames.com/spt-assets/234d2a56e9ab4e689b1a7f1c723f8d09/hellmaster-the-legend-of-dante-1y2j8.png",
      "md5": "cf119110f16ad4908ed0465d18a9278f",
      "width": 1200,
      "height": 1600,
      "size": 2073709,
      "uploadedDate": "2025-05-11T16:28:43.400Z",
      "alt": "Download Hellmaster: The Legend of Dante Offer"
    }
  ],
  "categories": [
    {
      "path": "games"
    },
    {
      "path": "applications"
    }
  ],
  "namespace": "fbd7234e063344a6aee161d0ca552064",
  "status": "ACTIVE",
  "creationDate": "2025-07-02T08:00:19.745Z",
  "lastModifiedDate": "2025-07-02T08:00:19.745Z",
  "customAttributes": {
    "FolderName": {
      "type": "STRING",
      "value": "HellmasterTheLegendoPWBim"
    }
  },
  "entitlementName": "daf05c7b040f41bfaec80178d159206c",
  "entitlementType": "EXECUTABLE",
  "itemType": "DURABLE",
  "releaseInfo": [
    {
      "id": "b43cbb3fc8c34b429d9cd15e58deac8c",
      "appId": "fe6124dbf265457a8424d90832937c0d",
      "platform": [
        "Windows"
      ]
    }
  ],
  "developer": "Dante Games",
  "developerId": "o-8nrzgr2nthjk6jugqps7wrpz5crj85",
  "endOfSupport": false,
  "requiresSecureAccount": false,
  "unsearchable": false
}