{
  "id": "e7833dcfb8c34b0ba3f898ae2fe8c480",
  "title": "Armory: Drone Tank",
  "description": "Armory: Drone Tank",
  "keyImages": [
    {
      "type": "DieselGameBox",
      "url": "https://cdn1.epicgames.com/spt-assets/3f36cddc373248019ba10ba9b9a12505/armory-drone-tank-1gpfk.png",
      "md5": "59543b3056727584b2ef356ff54b2a5c",
      "width": 2560,
      "height": 1440,
      "size": 4013555,
      "uploadedDate": "2025-06-05T17:48:42.120Z",
      "alt": "Armory: Drone Tank Offer"
    },
    {
      "type": "DieselGameBoxTall",
      "url": "https://cdn1.epicgames.com/spt-assets/3f36cddc373248019ba10ba9b9a12505/armory-drone-tank-naeg3.png",
      "md5": "071a3b460baca25e432f1f5bec8e35b6",
      "width": 1200,
      "height": 1600,
      "size": 2093369,
      "uploadedDate": "2025-06-05T17:48:42.251Z",
      "alt": "Download Armory: Drone Tank Offer"
    }
  ],
  "categories": [
    {
      "path": "games"
    },
    {
      "path": "applications"
    }
  ],
  "namespace": "f0c65ef156074fbe9fb370a861340461",
  "status": "ACTIVE",
  "creationDate": "2025-06-12T17:07:46.977Z",
  "lastModifiedDate": "2025-06-12T17:07:46.977Z",
  "customAttributes": {
    "FolderName": {
      "type": "STRING",
      "value": "ArmoryDroneTankslXJQ"
    }
  },
  "entitlementName": "e7833dcfb8c34b0ba3f898ae2fe8c480",
  "entitlementType": "EXECUTABLE",
  "itemType": "DURABLE",
  "releaseInfo": [
    {
      "id": "28e73654b2174448a81751888c4c8a16",
      "appId": "b5c7de47f83045d1aff25a73a891b936"
    }
  ],
  "developer": "Daefiant Armory GS",
  "developerId": "o-mdqa7lyaazskkuuq3zawczlf76pe34",
  "endOfSupport": false,
  "requiresSecureAccount": false,
  "unsearchable": false
}