{
  "id": "eb32f64a55ae466ab04a4b5e3dc96e99",
  "title": "DevGeneralAudience",
  "description": "DevGeneralAudience",
  "categories": [
    {
      "path": "audience"
    },
    {
      "path": "public"
    }
  ],
  "namespace": "89d646389bb544b4866e338426aefd41",
  "status": "ACTIVE",
  "creationDate": "2023-03-15T15:45:06.403Z",
  "lastModifiedDate": "2026-01-14T18:39:14.910Z",
  "entitlementName": "eb32f64a55ae466ab04a4b5e3dc96e99",
  "entitlementType": "AUDIENCE",
  "itemType": "DURABLE",
  "releaseInfo": [],
  "developer": "Serafini Productions",
  "developerId": "o-wnjre5sz9z8p2d2anuz27k5a2m9jcw",
  "endOfSupport": false,
  "requiresSecureAccount": false,
  "unsearchable": false
}