{
  "id": "eca0f3680b494e91ad5f058b34f20d1f",
  "title": "Cosmetics Collection Chest – Fleeting Traces_ConsumableAudience",
  "description": "Cosmetics Collection Chest – Fleeting Traces_ConsumableAudience",
  "categories": [
    {
      "path": "audience"
    },
    {
      "path": "public"
    }
  ],
  "namespace": "ceb703de37854cda9932d2f9dd531520",
  "status": "ACTIVE",
  "creationDate": "2026-02-10T09:18:24.166Z",
  "lastModifiedDate": "2026-02-10T09:18:24.166Z",
  "entitlementName": "eca0f3680b494e91ad5f058b34f20d1f",
  "entitlementType": "AUDIENCE",
  "itemType": "CONSUMABLE",
  "developer": "Hong Kong Spiral Rising Technology Co., Limited",
  "developerId": "o-hz9vqg8bt7t5bjhcx7mqq75x5te55c",
  "useCount": 1,
  "endOfSupport": false,
  "requiresSecureAccount": false,
  "unsearchable": false
}