{
  "id": "ed019950da014fb5827b954587db183d",
  "title": "DevGeneralAudience",
  "description": "DevGeneralAudience",
  "categories": [
    {
      "path": "audience"
    },
    {
      "path": "public"
    }
  ],
  "namespace": "1dd7c796d9c443cfa3ae23e0cafce760",
  "status": "ACTIVE",
  "creationDate": "2025-03-28T23:00:35.210Z",
  "lastModifiedDate": "2025-03-28T23:00:35.516Z",
  "entitlementName": "ed019950da014fb5827b954587db183d",
  "entitlementType": "AUDIENCE",
  "itemType": "DURABLE",
  "releaseInfo": [],
  "developer": "Dream on a Stick Ltd",
  "developerId": "o-5y9lq8hbxfm7p2fb7ymfqc5vkf7zy3",
  "endOfSupport": false,
  "requiresSecureAccount": false,
  "unsearchable": false
}