{
  "id": "f5986616386241ddb7aa8afc373c93e4",
  "title": "FortniteDevPlaytestP_StWContent",
  "description": "FortniteDevPlaytestP_StWContent",
  "categories": [
    {
      "path": "addons"
    },
    {
      "path": "applications"
    }
  ],
  "namespace": "fn",
  "status": "ACTIVE",
  "creationDate": "2026-05-18T16:53:01.500Z",
  "lastModifiedDate": "2026-05-22T20:08:51.884Z",
  "customAttributes": {
    "remove_for_account_deprovision": {
      "type": "STRING",
      "value": "true"
    },
    "UseAccessControl": {
      "type": "STRING",
      "value": "false"
    },
    "AdditionalCommandLine": {
      "type": "STRING",
      "value": "-epicapp=FortniteDevPlaytestP -IslandOverride=campaign"
    },
    "CanSkipKoreanIdVerification": {
      "type": "STRING",
      "value": "true"
    }
  },
  "entitlementName": "f5986616386241ddb7aa8afc373c93e4",
  "entitlementType": "EXECUTABLE",
  "itemType": "DURABLE",
  "releaseInfo": [
    {
      "id": "0b4a6ae23b5e4c44a5ff435153d8f48c",
      "appId": "1a9c84acde6e4fb49de5f7e30828439f",
      "platform": [
        "Windows"
      ]
    }
  ],
  "developer": "Epic Games",
  "developerId": "o-aa83a0a9bc45e98c80c1b1c9d92e9e",
  "endOfSupport": false,
  "requiresSecureAccount": false,
  "unsearchable": false
}