{
  "id": "f6b79dca402b47819addbecb023f1f70",
  "title": "PrePurchaseDevGeneralAudience",
  "description": "PrePurchaseDevGeneralAudience",
  "categories": [
    {
      "path": "audience"
    },
    {
      "path": "public"
    }
  ],
  "namespace": "08d6df03616c42388556ce5fc1366d3d",
  "status": "ACTIVE",
  "creationDate": "2025-04-17T05:55:29.751Z",
  "lastModifiedDate": "2025-05-22T01:32:35.626Z",
  "entitlementName": "f6b79dca402b47819addbecb023f1f70",
  "entitlementType": "AUDIENCE",
  "itemType": "DURABLE",
  "developer": "505 Games",
  "developerId": "o-cul2z53mrw3bxltv63v68rgd4b3w52",
  "endOfSupport": false,
  "requiresSecureAccount": false,
  "unsearchable": false
}