{
  "id": "fa394bf5d4fb4a7bb437576725819117",
  "title": "gustavus GeneralAudience",
  "description": "gustavus GeneralAudience",
  "keyImages": [],
  "categories": [
    {
      "path": "audience"
    },
    {
      "path": "public"
    }
  ],
  "namespace": "1298707fe40241e284fdf1ae9fbdc6b5",
  "status": "ACTIVE",
  "creationDate": "2021-09-14T00:46:37.690Z",
  "lastModifiedDate": "2021-11-02T15:44:33.327Z",
  "customAttributes": {},
  "entitlementName": "fa394bf5d4fb4a7bb437576725819117",
  "entitlementType": "AUDIENCE",
  "itemType": "DURABLE",
  "releaseInfo": [],
  "developer": "Wired Productions",
  "developerId": "o-r83qbqhwd8y5y5r6e9x62vtrsd9mqm",
  "eulaIds": [
    "egstore"
  ],
  "endOfSupport": false,
  "requiresSecureAccount": false,
  "unsearchable": true
}