{
  "id": "fec146af2f834669835ce761957f12f2",
  "title": "战令128档_ConsumableAudience",
  "description": "战令128档_ConsumableAudience",
  "categories": [
    {
      "path": "audience"
    },
    {
      "path": "public"
    }
  ],
  "namespace": "ceb703de37854cda9932d2f9dd531520",
  "status": "ACTIVE",
  "creationDate": "2025-10-11T07:14:11.076Z",
  "lastModifiedDate": "2026-02-09T20:26:06.350Z",
  "entitlementName": "fec146af2f834669835ce761957f12f2",
  "entitlementType": "AUDIENCE",
  "itemType": "CONSUMABLE",
  "developer": "Hong Kong Spiral Rising Technology Co., Limited",
  "developerId": "o-hz9vqg8bt7t5bjhcx7mqq75x5te55c",
  "useCount": 1,
  "endOfSupport": false,
  "requiresSecureAccount": false,
  "unsearchable": false
}