{
  "id": "fff607f81c4048abaaf9e40b59ebf86d",
  "title": "Kopi",
  "description": "Kopi",
  "keyImages": [
    {
      "type": "DieselGameBox",
      "url": "https://cdn1.epicgames.com/spt-assets/99f8278e8a6147e7b2680b47191f74e3/kopi-10tu4.png",
      "md5": "e4fd01008d089d1096bca469164ca367",
      "width": 2560,
      "height": 1440,
      "size": 2142604,
      "uploadedDate": "2025-03-10T12:39:58.334Z",
      "alt": "Kopi Offer"
    },
    {
      "type": "DieselGameBoxTall",
      "url": "https://cdn1.epicgames.com/spt-assets/99f8278e8a6147e7b2680b47191f74e3/kopi-1jil7.png",
      "md5": "af43d016e15cd3f676874c415bbb2275",
      "width": 1200,
      "height": 1600,
      "size": 1483148,
      "uploadedDate": "2025-03-10T12:40:28.369Z",
      "alt": "Download Kopi Offer"
    }
  ],
  "categories": [
    {
      "path": "games"
    },
    {
      "path": "applications"
    }
  ],
  "namespace": "1dd7c796d9c443cfa3ae23e0cafce760",
  "status": "ACTIVE",
  "creationDate": "2025-03-28T23:00:35.212Z",
  "lastModifiedDate": "2025-03-28T23:00:35.212Z",
  "customAttributes": {
    "FolderName": {
      "type": "STRING",
      "value": "KopiGame"
    }
  },
  "entitlementName": "fff607f81c4048abaaf9e40b59ebf86d",
  "entitlementType": "EXECUTABLE",
  "itemType": "DURABLE",
  "releaseInfo": [
    {
      "id": "c9c8af37d1074fad8ffef4b4906ebbca",
      "appId": "cda714eccda5462099aea866cfae4eb2",
      "platform": [
        "Windows"
      ]
    }
  ],
  "developer": "Dream on a Stick Ltd",
  "developerId": "o-5y9lq8hbxfm7p2fb7ymfqc5vkf7zy3",
  "endOfSupport": false,
  "applicationId": "fghi4567j4GDIlDi4TzDl5oR9cT0MvGw",
  "requiresSecureAccount": false,
  "unsearchable": false
}